memory_cache/__init__.py
memory_cache/algorithms.py
memory_cache/api.py
memory_cache/storage.py
memory_cache/timer.py
csy_memory_cache-0.1.2.dist-info/LICENSE
csy_memory_cache-0.1.2.dist-info/METADATA
csy_memory_cache-0.1.2.dist-info/WHEEL
csy_memory_cache-0.1.2.dist-info/top_level.txt
csy_memory_cache-0.1.2.dist-info/RECORD
